Metadata-Version: 2.1
Name: simplepkg
Version: 0.4.3
Summary: Simple python package scaffolding utility.
Home-page: https://gitlab.com/b5n/simplepkg
Author: Brandon Nunez
Author-email: b@bnunez.com
License: UNKNOWN
Platform: UNKNOWN
Classifier: Programming Language :: Python :: 3
Classifier: License :: OSI Approved :: MIT License
Requires-Python: >=3.6
License-File: LICENSE
Requires-Dist: setuptools
Requires-Dist: pathlib
